metal_flash_sdpa/_C.cpython-312-darwin.so
metal_flash_sdpa/__init__.py
metal_flash_sdpa/_custom_ops.py
metal_flash_sdpa/_ops.py
metal_flash_sdpa-0.1.2.dist-info/METADATA
metal_flash_sdpa-0.1.2.dist-info/WHEEL
metal_flash_sdpa-0.1.2.dist-info/top_level.txt
metal_flash_sdpa-0.1.2.dist-info/RECORD
